msgraph_async/__init__.py
msgraph_async/client/__init__.py
msgraph_async/client/client.py
msgraph_async/client/tests/__init__.py
msgraph_async/client/tests/test_client.py
msgraph_async/common/__init__.py
msgraph_async/common/constants.py
msgraph_async/common/exceptions.py
msgraph_async/common/odata_query.py
msgraph_async/common/tests/__init__.py
msgraph_async/common/tests/test_odata_query.py
msgraph_async/common/tests/test_subscription_resource.py
msgraph_async-0.2.2.dist-info/LICENSE
msgraph_async-0.2.2.dist-info/METADATA
msgraph_async-0.2.2.dist-info/WHEEL
msgraph_async-0.2.2.dist-info/top_level.txt
msgraph_async-0.2.2.dist-info/RECORD
